{
  "nodes": [
    {
      "name": "Flavio", "age": 36
    },
    {
      "name": "Roger", "age": 7
    },
    {
      "name": "MY", "age": 30
    },
    {
      "name": "Taylor", "age": 16
    },
    {
      "name": "Dan", "age": 33
    },
    {
      "name": "Kevin", "age": 5
    },
    {
      "id": 2,
      "title": "First post",
      "description": "Content of the first post",
      "author": "Flavio"
    },
    {
      "id": 3,
      "title": "Second post",
      "description": "Content of the second post",
      "author": "Roger"
    },
    {
      "id": 11,
      "title": "South Dakota post",
      "description": "hey all you cool cats",
      "author": "Dan"
    },
    {
      "id": 12,
      "title": "Florida post",
      "description": "hey all you cool cats",
      "author": "Taylor"
    },
    {
      "id": 13,
      "title": "NYC post",
      "description": "hey all you cool cats",
      "author": "Kevin"
    },
    {
      "id": 14,
      "title": "hello",
      "description": "hey all you cool cats",
      "author": "Taylor"
    },
    {
      "id": 15,
      "title": "Tiger King post",
      "description": "hey all you cool cats",
      "author": "Dan"
    },
    {
      "id": 16,
      "title": "tired of pasta",
      "description": "hey all you cool cats",
      "author": "MY"
    },
    {
      "id": 17,
      "title": "recipes",
      "description": "hey all you cool cats",
      "author": "Kevin"
    },
    {
      "id": 18,
      "title": "mongolia",
      "description": "hey all you cool cats",
      "author": "Dan"
    }
  ],
  "links": [
    {
      "source": "Flavio", "target": "Flavio"
    },
    {
      "source": "Roger", "target": "Roger"
    },
    {
      "source": "Dan", "target": "Dan"
    },
    {
      "source": "Taylor", "target": "Taylor"
    },
    {
      "source": "Kevin", "target": "Kevin"
    },
    {
      "source": "Taylor", "target": "Taylor"
    },
    {
      "source": "Dan", "target": "Dan"
    },
    {
      "source": "MY", "target": "MY"
    },
    {
      "source": "Kevin", "target": "Kevin"
    },
    {
      "source": "Dan", "target": "Dan"
    }
  ]
}